lagcorp/__init__.py
lagcorp/__main__.py
lagcorp/camper.py
lagcorp-1.0.2.dist-info/LICENSE
lagcorp-1.0.2.dist-info/METADATA
lagcorp-1.0.2.dist-info/WHEEL
lagcorp-1.0.2.dist-info/entry_points.txt
lagcorp-1.0.2.dist-info/top_level.txt
lagcorp-1.0.2.dist-info/RECORD
