Metadata-Version: 2.1
Name: lagcorp
Version: 1.0.2
Summary: A sample pypi upload.
Home-page: UNKNOWN
Author: iamrealbhuvi
Author-email: bhuvanesh19112001@gmail.com
License: MIT
Platform: UNKNOWN
Classifier: License :: OSI Approved :: MIT License
Classifier: Programming Language :: Python :: 3.6
Classifier: Programming Language :: Python :: 3.7
Classifier: Programming Language :: Python :: 3.8
